freezer/__init__.py
freezer/job.py
freezer/main.py
freezer/common/__init__.py
freezer/common/client_manager.py
freezer/common/config.py
freezer/engine/__init__.py
freezer/engine/engine.py
freezer/engine/manager.py
freezer/engine/glance/__init__.py
freezer/engine/glance/glance.py
freezer/engine/nova/__init__.py
freezer/engine/nova/nova.py
freezer/engine/osbrick/__init__.py
freezer/engine/osbrick/brick_utils.py
freezer/engine/osbrick/client.py
freezer/engine/osbrick/osbrick.py
freezer/engine/osbrick/volume_actions.py
freezer/engine/rsync/__init__.py
freezer/engine/rsync/pyrsync.py
freezer/engine/rsync/rsync.py
freezer/engine/rsyncv2/__init__.py
freezer/engine/rsyncv2/pyrsync.py
freezer/engine/rsyncv2/rsyncv2.py
freezer/engine/tar/__init__.py
freezer/engine/tar/tar.py
freezer/engine/tar/tar_builders.py
freezer/exceptions/__init__.py
freezer/exceptions/engine.py
freezer/exceptions/utils.py
freezer/lib/__init__.py
freezer/lib/pep3143daemon/__init__.py
freezer/lib/pep3143daemon/daemon.py
freezer/lib/pep3143daemon/pidfile.py
freezer/mode/__init__.py
freezer/mode/cinder.py
freezer/mode/cindernative.py
freezer/mode/fs.py
freezer/mode/glance.py
freezer/mode/mode.py
freezer/mode/mongo.py
freezer/mode/mysql.py
freezer/mode/nova.py
freezer/mode/sqlserver.py
freezer/openstack/__init__.py
freezer/openstack/admin.py
freezer/openstack/backup.py
freezer/openstack/osclients.py
freezer/openstack/restore.py
freezer/scheduler/__init__.py
freezer/scheduler/arguments.py
freezer/scheduler/daemon.py
freezer/scheduler/freezer_scheduler.py
freezer/scheduler/scheduler_job.py
freezer/scheduler/utils.py
freezer/scheduler/win_daemon.py
freezer/scheduler/win_service.py
freezer/scripts/vss.ps1
freezer/snapshot/__init__.py
freezer/snapshot/lvm.py
freezer/snapshot/snapshot.py
freezer/snapshot/vss.py
freezer/storage/__init__.py
freezer/storage/base.py
freezer/storage/exceptions.py
freezer/storage/fslike.py
freezer/storage/ftp.py
freezer/storage/local.py
freezer/storage/multiple.py
freezer-17.0.0.dist-info/AUTHORS
freezer-17.0.0.dist-info/LICENSE
freezer-17.0.0.dist-info/METADATA
freezer-17.0.0.dist-info/WHEEL
freezer-17.0.0.dist-info/entry_points.txt
freezer-17.0.0.dist-info/pbr.json
freezer-17.0.0.dist-info/top_level.txt
freezer-17.0.0.dist-info/RECORD
