Metadata-Version: 2.1
Name: freezer
Version: 17.0.0
Summary: The OpenStack Backup and Restore as a Service Platform
Home-page: https://docs.openstack.org/freezer/latest/
Author: OpenStack
Author-email: openstack-discuss@lists.openstack.org
License: Apache-2.0
Keywords: freezer,backup,openstack,restore,lvm,snapshot,mongodb,mysql
Classifier: Programming Language :: Python
Classifier: Programming Language :: Python :: Implementation :: CPython
Classifier: Programming Language :: Python :: 3 :: Only
Classifier: Programming Language :: Python :: 3
Classifier: Programming Language :: Python :: 3.9
Classifier: Programming Language :: Python :: 3.10
Classifier: Programming Language :: Python :: 3.11
Classifier: Programming Language :: Python :: 3.12
Classifier: Development Status :: 5 - Production/Stable
Classifier: Natural Language :: English
Classifier: Environment :: OpenStack
Classifier: Intended Audience :: Developers
Classifier: Intended Audience :: Information Technology
Classifier: Intended Audience :: System Administrators
Classifier: Operating System :: MacOS
Classifier: Operating System :: POSIX :: BSD :: FreeBSD
Classifier: Operating System :: POSIX :: BSD :: NetBSD
Classifier: Operating System :: POSIX :: BSD :: OpenBSD
Classifier: Operating System :: POSIX :: Linux
Classifier: Operating System :: Microsoft :: Windows
Classifier: Operating System :: Unix
Classifier: Topic :: System :: Archiving :: Backup
Classifier: Topic :: System :: Archiving :: Compression
Classifier: Topic :: System :: Archiving
Requires-Python: >=3.9
License-File: LICENSE
License-File: AUTHORS
Requires-Dist: pbr >=4.0.0
Requires-Dist: botocore >=1.5.1
Requires-Dist: setuptools !=24.0.0,!=34.0.0,!=34.0.1,!=34.0.2,!=34.0.3,!=34.1.0,!=34.1.1,!=34.2.0,!=34.3.0,!=34.3.1,!=34.3.2,!=36.2.0,>=21.0.0
Requires-Dist: python-swiftclient >=3.2.0
Requires-Dist: python-cinderclient >=3.3.0
Requires-Dist: python-glanceclient >=2.8.0
Requires-Dist: python-keystoneclient >=3.8.0
Requires-Dist: python-novaclient >=9.1.0
Requires-Dist: python-neutronclient >=6.7.0
Requires-Dist: python-freezerclient >=2.0.0
Requires-Dist: oslo.serialization >=5.5.0
Requires-Dist: oslo.utils >=7.3.0
Requires-Dist: oslo.log >=5.3.0
Requires-Dist: oslo.config >=9.4.0
Requires-Dist: oslo.service !=1.28.1,>=1.24.0
Requires-Dist: keystoneauth1 >=3.14.0
Requires-Dist: os-brick >=2.2.0
Requires-Dist: cryptography >=2.5
Requires-Dist: PyMySQL >=0.7.6
Requires-Dist: pymongo !=3.1,>=3.0.2
Requires-Dist: paramiko >=2.7.1
Requires-Dist: apscheduler >=3.0.5
Requires-Dist: psutil >=3.2.2
